{
	"success":true,
	"miaoshaActiveList":[ 
		{
			"id":1,
			"title":"色彩艳丽的口红眉笔",
			"desc":"这是title描述--MUSE冰淇淋MUSE冰淇淋MUSE冰淇淋MUSE冰淇淋MUSE冰淇淋MUSE冰淇淋MUSE冰淇",
			"quantity":113,
			"joinCount":6,
			"activePrice":"48.00",
			"originalPrice":"257.00",
			"star":4,
			"limit_time":17,
			"product":{
				"image":"img/itemlist2.png",
				"name":"Muse冰淇淋"
			}
		},
		{
			"id":2,
			"title":"色彩艳丽的口红眉笔",
			"desc":"这是title描述--MUSE冰淇淋MUSE冰淇淋MUSE冰淇淋MUSE冰淇淋MUSE冰淇淋MUSE冰淇淋MUSE冰淇",
			"quantity":113,
			"joinCount":6,
			"activePrice":"48.00",
			"originalPrice":"257.00",
			"star":4,
			"limit_time":13,
			"product":{
				"image":"img/photo.jpg",
				"name":"Muse冰淇淋"
			}
		},
		{
			"id":3,
			"title":"色彩艳丽的口红眉笔",
			"desc":"这是title描述--MUSE冰淇淋MUSE冰淇淋MUSE冰淇淋MUSE冰淇淋MUSE冰淇淋MUSE冰淇淋MUSE冰淇",
			"quantity":113,
			"joinCount":6,
			"activePrice":"48.00",
			"originalPrice":"257.00",
			"star":4,
			"limit_time":16,
			"product":{
				"image":"img/itemlist1.png",
				"name":"Muse冰淇淋"
			}
		},
		{
			"id":4,
			"title":"色彩艳丽的口红眉笔",
			"desc":"这是title描述--MUSE冰淇淋MUSE冰淇淋MUSE冰淇淋MUSE冰淇淋MUSE冰淇淋MUSE冰淇淋MUSE冰淇",
			"quantity":113,
			"joinCount":6,
			"activePrice":"48.00",
			"originalPrice":"257.00",
			"star":4,
			"limit_time":19,
			"product":{
				"image":"img/itemlist2.png",
				"name":"Muse冰淇淋"
			}
		},
		{
			"id":5,
			"title":"色彩艳丽的口红眉笔",
			"desc":"这是title描述--MUSE冰淇淋MUSE冰淇淋MUSE冰淇淋MUSE冰淇淋MUSE冰淇淋MUSE冰淇淋MUSE冰淇",
			"quantity":113,
			"joinCount":6,
			"activePrice":"48.00",
			"originalPrice":"257.00",
			"star":4,
			"limit_time":19,
			"product":{
				"image":"img/itemlist1.png",
				"name":"Muse冰淇淋"
			}
		},
		{
			"id":6,
			"title":"色彩艳丽的口红眉笔",
			"desc":"这是title描述--MUSE冰淇淋MUSE冰淇淋MUSE冰淇淋MUSE冰淇淋MUSE冰淇淋MUSE冰淇淋MUSE冰淇",
			"quantity":113,
			"joinCount":6,
			"activePrice":"48.00",
			"originalPrice":"257.00",
			"star":4,
			"limit_time":23,
			"product":{
				"image":"img/itemlist2.png",
				"name":"Muse冰淇淋"
			}
		},
		{
			"id":7,
			"title":"色彩艳丽的口红眉笔",
			"desc":"这是title描述--MUSE冰淇淋MUSE冰淇淋MUSE冰淇淋MUSE冰淇淋MUSE冰淇淋MUSE冰淇淋MUSE冰淇",
			"quantity":113,
			"joinCount":6,
			"activePrice":"48.00",
			"originalPrice":"257.00",
			"star":4,
			"limit_time":15,
			"product":{
				"image":"img/itemlist2.png",
				"name":"Muse冰淇淋"
			}
		}
	]
}